openai/__init__.py
openai/api_requestor.py
openai/error.py
openai/object_classes.py
openai/openai_object.py
openai/openai_response.py
openai/py.typed
openai/util.py
openai/validators.py
openai/version.py
openai/api_resources/__init__.py
openai/api_resources/answer.py
openai/api_resources/classification.py
openai/api_resources/completion.py
openai/api_resources/engine.py
openai/api_resources/error_object.py
openai/api_resources/file.py
openai/api_resources/fine_tune.py
openai/api_resources/model.py
openai/api_resources/search.py
openai/api_resources/abstract/__init__.py
openai/api_resources/abstract/api_resource.py
openai/api_resources/abstract/createable_api_resource.py
openai/api_resources/abstract/deletable_api_resource.py
openai/api_resources/abstract/engine_api_resource.py
openai/api_resources/abstract/listable_api_resource.py
openai/api_resources/abstract/nested_resource_class_methods.py
openai/api_resources/abstract/updateable_api_resource.py
openai/api_resources/experimental/__init__.py
openai/api_resources/experimental/completion_config.py
openai/data/ca-certificates.crt
openai_slim-0.11.7.dist-info/LICENSE
openai_slim-0.11.7.dist-info/METADATA
openai_slim-0.11.7.dist-info/WHEEL
openai_slim-0.11.7.dist-info/top_level.txt
openai_slim-0.11.7.dist-info/RECORD
